{
  "title": "1",
  "seeds": [
    {
      "id": 1,
      "date": "",
      "teams": [
        {
          "name": "budi",
          "score": 30,
          "gambar": "/gambar/5foyomg.png",
          "alamat": "sukarame",
          "tim": "madun"
        },
        {
          "name": "ikbal",
          "score": 0,
          "gambar": "/gambar/laheny7.png",
          "alamat": "sekret",
          "tim": "medin"
        }
      ]
    },
    {
      "id": 2,
      "date": "",
      "teams": [
        {
          "name": "",
          "score": 0,
          "gambar": "",
          "alamat": "",
          "tim": ""
        },
        {
          "name": "",
          "score": 0,
          "gambar": "",
          "alamat": "",
          "tim": ""
        }
      ]
    }
  ],
  "id": "1"
}